feature_clock/__init__.py
feature_clock/graph.py
feature_clock/plot.py
feature_clock-1.0.2.dist-info/LICENSE
feature_clock-1.0.2.dist-info/METADATA
feature_clock-1.0.2.dist-info/WHEEL
feature_clock-1.0.2.dist-info/top_level.txt
feature_clock-1.0.2.dist-info/RECORD
